YoullDownload
youlldownload
