Metadata-Version: 1.1
Name: YoullDownload
Version: 0.4
Summary: Grab from a remote site page all resources that a browser will probably download visiting the page
Home-page: https://github.com/RedTurtle/YoullDownload
Author: RedTurtle Technology
Author-email: sviluppoplone@redturtle.it
License: GPL
Keywords: crawler log web
Platform: UNKNOWN
Classifier: Development Status :: 4 - Beta
Classifier: License :: OSI Approved :: GNU General Public License (GPL)
Classifier: Operating System :: OS Independent
Classifier: Programming Language :: Python
Classifier: Programming Language :: Python :: 2.7
Classifier: Topic :: Utilities
Classifier: Topic :: Internet :: WWW/HTTP
